permtab/__init__.py
permtab/core.py
permtab/exceptions.py
permtab/fileedit.py
permtab-0.1.0.dist-info/LICENSE
permtab-0.1.0.dist-info/METADATA
permtab-0.1.0.dist-info/WHEEL
permtab-0.1.0.dist-info/top_level.txt
permtab-0.1.0.dist-info/RECORD
