Metadata-Version: 2.1
Name: permtab
Version: 0.1.0
Summary: A simple permission rule parsing library.
Author-email: HivertMoZara <worldmozara@163.com>
License: MIT
Project-URL: Homepage, https://github.com/NCBM/permtab
Project-URL: Repository, https://github.com/NCBM/permtab
Requires-Python: >=3.8
License-File: LICENSE
